[1,["1c1cf0108@6c48a"],["_textureSource"],["cc.SpriteFrame"],0,[[[{"name":"Coin_14","rect":{"x":3,"y":163,"width":73,"height":73},"offset":{"x":-0.5,"y":0.5},"originalSize":{"width":80,"height":80},"rotated":false,"capInsets":[0,0,0,0],"packable":true,"pixelsToUnit":100,"pivot":{"x":0.5,"y":0.5},"meshType":0}],[0],0,[0],[0],[0]],[[{"name":"Coin_6","rect":{"x":3,"y":83,"width":44,"height":74},"offset":{"x":0,"y":0},"originalSize":{"width":48,"height":80},"rotated":false,"capInsets":[0,0,0,0],"packable":true,"pixelsToUnit":100,"pivot":{"x":0.5,"y":0.5},"meshType":0}],[0],0,[0],[0],[0]],[[{"name":"Coin_7","rect":{"x":81,"y":477,"width":36,"height":71},"offset":{"x":0,"y":0.5},"originalSize":{"width":40,"height":72},"rotated":false,"capInsets":[0,0,0,0],"packable":true,"pixelsToUnit":100,"pivot":{"x":0.5,"y":0.5},"meshType":0}],[0],0,[0],[0],[0]],[[{"name":"Coin_9","rect":{"x":75,"y":321,"width":36,"height":71},"offset":{"x":0,"y":0.5},"originalSize":{"width":40,"height":72},"rotated":false,"capInsets":[0,0,0,0],"packable":true,"pixelsToUnit":100,"pivot":{"x":0.5,"y":0.5},"meshType":0}],[0],0,[0],[0],[0]],[[{"name":"Coin_1","rect":{"x":53,"y":83,"width":72,"height":71},"offset":{"x":0,"y":0.5},"originalSize":{"width":72,"height":72},"rotated":true,"capInsets":[0,0,0,0],"packable":true,"pixelsToUnit":100,"pivot":{"x":0.5,"y":0.5},"meshType":0}],[0],0,[0],[0],[0]],[[{"name":"Coin_8","rect":{"x":3,"y":527,"width":24,"height":72},"offset":{"x":0,"y":0},"originalSize":{"width":24,"height":72},"rotated":true,"capInsets":[0,0,0,0],"packable":true,"pixelsToUnit":100,"pivot":{"x":0.5,"y":0.5},"meshType":0}],[0],0,[0],[0],[0]],[[{"name":"Coin_11","rect":{"x":3,"y":478,"width":43,"height":72},"offset":{"x":-0.5,"y":0},"originalSize":{"width":48,"height":72},"rotated":true,"capInsets":[0,0,0,0],"packable":true,"pixelsToUnit":100,"pivot":{"x":0.5,"y":0.5},"meshType":0}],[0],0,[0],[0],[0]],[[{"name":"Coin_13","rect":{"x":58,"y":400,"width":59,"height":71},"offset":{"x":-0.5,"y":0.5},"originalSize":{"width":64,"height":72},"rotated":false,"capInsets":[0,0,0,0],"packable":true,"pixelsToUnit":100,"pivot":{"x":0.5,"y":0.5},"meshType":0}],[0],0,[0],[0],[0]],[[{"name":"Coin_3","rect":{"x":3,"y":321,"width":66,"height":73},"offset":{"x":0,"y":0.5},"originalSize":{"width":72,"height":80},"rotated":false,"capInsets":[0,0,0,0],"packable":true,"pixelsToUnit":100,"pivot":{"x":0.5,"y":0.5},"meshType":0}],[0],0,[0],[0],[0]],[[{"name":"Coin_2","rect":{"x":3,"y":242,"width":73,"height":73},"offset":{"x":-0.5,"y":0.5},"originalSize":{"width":80,"height":80},"rotated":false,"capInsets":[0,0,0,0],"packable":true,"pixelsToUnit":100,"pivot":{"x":0.5,"y":0.5},"meshType":0}],[0],0,[0],[0],[0]],[[{"name":"Coin_4","rect":{"x":60,"y":3,"width":64,"height":73},"offset":{"x":0,"y":0.5},"originalSize":{"width":64,"height":80},"rotated":false,"capInsets":[0,0,0,0],"packable":true,"pixelsToUnit":100,"pivot":{"x":0.5,"y":0.5},"meshType":0}],[0],0,[0],[0],[0]],[[{"name":"Coin_12","rect":{"x":3,"y":400,"width":49,"height":72},"offset":{"x":-0.5,"y":0},"originalSize":{"width":56,"height":72},"rotated":false,"capInsets":[0,0,0,0],"packable":true,"pixelsToUnit":100,"pivot":{"x":0.5,"y":0.5},"meshType":0}],[0],0,[0],[0],[0]],[[{"name":"Coin_5","rect":{"x":3,"y":3,"width":51,"height":74},"offset":{"x":-0.5,"y":0},"originalSize":{"width":56,"height":80},"rotated":false,"capInsets":[0,0,0,0],"packable":true,"pixelsToUnit":100,"pivot":{"x":0.5,"y":0.5},"meshType":0}],[0],0,[0],[0],[0]],[[{"name":"Coin_10","rect":{"x":82,"y":161,"width":28,"height":72},"offset":{"x":0,"y":0},"originalSize":{"width":32,"height":72},"rotated":false,"capInsets":[0,0,0,0],"packable":true,"pixelsToUnit":100,"pivot":{"x":0.5,"y":0.5},"meshType":0}],[0],0,[0],[0],[0]]]]
